odoo/addons/l10n_nl_tax_invoice_basis/README.rst
odoo/addons/l10n_nl_tax_invoice_basis/__init__.py
odoo/addons/l10n_nl_tax_invoice_basis/__manifest__.py
odoo/addons/l10n_nl_tax_invoice_basis/i18n/l10n_nl_tax_invoice_basis.pot
odoo/addons/l10n_nl_tax_invoice_basis/i18n/nl.po
odoo/addons/l10n_nl_tax_invoice_basis/models/__init__.py
odoo/addons/l10n_nl_tax_invoice_basis/models/account_invoice.py
odoo/addons/l10n_nl_tax_invoice_basis/models/account_move_line.py
odoo/addons/l10n_nl_tax_invoice_basis/models/account_tax.py
odoo/addons/l10n_nl_tax_invoice_basis/models/res_company.py
odoo/addons/l10n_nl_tax_invoice_basis/models/res_config_settings.py
odoo/addons/l10n_nl_tax_invoice_basis/static/description/icon.png
odoo/addons/l10n_nl_tax_invoice_basis/tests/__init__.py
odoo/addons/l10n_nl_tax_invoice_basis/tests/test_tax_invoice_basis.py
odoo/addons/l10n_nl_tax_invoice_basis/views/res_config_settings.xml
odoo11_addon_l10n_nl_tax_invoice_basis-11.0.1.0.0.99.dev5.dist-info/METADATA
odoo11_addon_l10n_nl_tax_invoice_basis-11.0.1.0.0.99.dev5.dist-info/WHEEL
odoo11_addon_l10n_nl_tax_invoice_basis-11.0.1.0.0.99.dev5.dist-info/top_level.txt
odoo11_addon_l10n_nl_tax_invoice_basis-11.0.1.0.0.99.dev5.dist-info/RECORD
